main.py
base_one-1.0.2.dist-info/METADATA
base_one-1.0.2.dist-info/WHEEL
base_one-1.0.2.dist-info/top_level.txt
base_one-1.0.2.dist-info/RECORD
