Metadata-Version: 2.4
Name: base-one
Version: 1.0.2
Summary: Implements Base1 (from qntm) in a python library
License-Expression: CC0-1.0
